gpt_resolve/__init__.py
gpt_resolve/pdf_generator.py
gpt_resolve/resolve.py
gpt_resolve/utils.py
gpt_resolve-0.2.2.dist-info/LICENSE
gpt_resolve-0.2.2.dist-info/METADATA
gpt_resolve-0.2.2.dist-info/WHEEL
gpt_resolve-0.2.2.dist-info/entry_points.txt
gpt_resolve-0.2.2.dist-info/RECORD
