Metadata-Version: 2.1
Name: gpt-resolve
Version: 0.2.2
Summary: GPT solutions for Brazilian university entrance exams.
Home-page: https://github.com/lgabs/gpt-resolve
License: MIT
Keywords: gpt,education,exam-solving,brazil
Author: Luan Fernandes
Author-email: luangabriel70@gmail.com
Requires-Python: >=3.9,<4.0
Classifier: Development Status :: 3 - Alpha
Classifier: Intended Audience :: Education
Classifier: License :: OSI Approved :: MIT License
Classifier: Programming Language :: Python :: 3
Classifier: Programming Language :: Python :: 3.9
Classifier: Programming Language :: Python :: 3.10
Classifier: Programming Language :: Python :: 3.11
Requires-Dist: openai (>=1.54.3,<2.0.0)
Requires-Dist: pylatex (>=1.4.2,<2.0.0)
Requires-Dist: python-dotenv (>=1.0.1,<2.0.0)
Requires-Dist: tqdm (>=4.67.0,<5.0.0)
Requires-Dist: typer (>=0.13.0,<0.14.0)
Project-URL: Repository, https://github.com/lgabs/gpt-resolve
